athame/__init__.py
athame/ast.py
athame/exceptions.py
athame/lexer.py
athame/parser.py
athame/trie.py
athame-0.1.0.dist-info/LICENSE
athame-0.1.0.dist-info/WHEEL
athame-0.1.0.dist-info/METADATA
athame-0.1.0.dist-info/RECORD
