Metadata-Version: 2.1
Name: athame
Version: 0.1.0
Summary: A tool for scheduling allowed/forbidden blocks of execution time for daemon processes.
License: MIT
Author: Graham Drakeley
Author-email: gt.drakeley@gmail.com
Requires-Python: >=3.8,<4.0
Classifier: License :: OSI Approved :: MIT License
Classifier: Programming Language :: Python :: 3
Classifier: Programming Language :: Python :: 3.8
Classifier: Programming Language :: Python :: 3.9
Requires-Dist: pendulum (>=2.1.2,<3.0.0)
Requires-Dist: py-buzz (>=2.1.3,<3.0.0)
Requires-Dist: pydantic (>=1.8.2,<2.0.0)
